README.rst
setup.py
db_backup/__init__.py
db_backup/commands.py
db_backup/databases.py
db_backup/encryption.py
db_backup/errors.py
db_backup/processes.py
db_backup.egg-info/PKG-INFO
db_backup.egg-info/SOURCES.txt
db_backup.egg-info/dependency_links.txt
db_backup.egg-info/requires.txt
db_backup.egg-info/top_level.txt