Metadata-Version: 1.0
Name: db-backup
Version: 0.1.1
Summary: Code for creating encrypted backups of databases
Home-page: http://db-backup.readthedocs.org
Author: Stephen Moore
Author-email: stephen@delfick.com
License: WTFPL
Keywords: database encrypted backup restore
Platform: UNKNOWN
